[
  {
    "id": "1000",
    "name": "Kingston FURY Beast RGB 32GB DDR5-6000",
    "brand": "Kingston",
    "price": 199.99,
    "description": "High-performance DDR5 memory with RGB lighting.",
    "specs": {
      "Capacity": "32GB (2x16GB)",
      "Speed": "6000MHz",
      "Latency": "CL36",
      "Voltage": "1.35V",
      "RGB": "Yes"
    },
    "capacity": "32GB",
    "speed": "6000MHz",
    "type": "DDR5",
    "image": "/images/components/ram/Kingston_FURY-Beast-RGB_2023_2-DIMMs_05DEC.jpg"
  },
  {
    "id": "1001",
    "name": "Corsair Vengeance RGB Pro 32GB DDR4-3600",
    "brand": "Corsair",
    "price": 129.99,
    "description": "Optimized for Intel and AMD DDR4 platforms with RGB.",
    "specs": {
      "Capacity": "32GB (2x16GB)",
      "Speed": "3600MHz",
      "Latency": "CL18",
      "Voltage": "1.35V",
      "RGB": "Yes"
    },
    "capacity": "32GB",
    "speed": "3600MHz",
    "type": "DDR4",
    "image": "/images/components/ram/ktc-beast-ddr4-dimm-2_front_hr (1).jpg"
  },
  {
    "id": "1002",
    "name": "Corsair Vengeance 32GB DDR5-5600",
    "brand": "Corsair",
    "price": 169.99,
    "description": "High-performance DDR5 memory for latest platforms.",
    "specs": {
      "Capacity": "32GB (2x16GB)",
      "Speed": "5600MHz",
      "Latency": "CL36",
      "Voltage": "1.25V",
      "RGB": "No"
    },
    "capacity": "32GB",
    "speed": "5600MHz",
    "type": "DDR5",
    "image": "/images/components/ram/Untitled design (19).png"
  }
]